briefcase_media/media.py
briefcase_media-0.4.0.dist-info/METADATA
briefcase_media-0.4.0.dist-info/WHEEL
briefcase_media-0.4.0.dist-info/RECORD
